retoolrpc/__init__.py
retoolrpc/rpc.py
retoolrpc/utils/api.py
retoolrpc/utils/errors.py
retoolrpc/utils/helpers.py
retoolrpc/utils/logger.py
retoolrpc/utils/polling.py
retoolrpc/utils/schema.py
retoolrpc/utils/types.py
retoolrpc/version.py
retoolrpc-0.1.2.dist-info/LICENSE
retoolrpc-0.1.2.dist-info/METADATA
retoolrpc-0.1.2.dist-info/WHEEL
retoolrpc-0.1.2.dist-info/RECORD
